<annotation>
	<folder>Data</folder>
	<filename>7137.jpg</filename>
	<path>/home/sachin/datascience/RetinanetTutorial/PlumsVOC/JPEGImages/7137.jpg</path>
	<source>
		<database>Unspecified</database>
	</source>
	<size>
		<width>1920</width>
		<height>1080</height>
		<depth>3</depth>
	</size>
	<object>
		<name>Perching</name>
		<pose>Unspecified</pose>
		<truncated>0</truncated>
		<difficult>0</difficult>
		<bndbox>
			<xmin>101</xmin>
			<ymin>761</ymin>
			<xmax>252</xmax>
			<ymax>923</ymax>
		</bndbox>
	</object>
	<object>
		<name>Perching</name>
		<pose>Unspecified</pose>
		<truncated>0</truncated>
		<difficult>0</difficult>
		<bndbox>
			<xmin>157</xmin>
			<ymin>217</ymin>
			<xmax>254</xmax>
			<ymax>346</ymax>
		</bndbox>
	</object>
	<object>
		<name>Perching</name>
		<pose>Unspecified</pose>
		<truncated>0</truncated>
		<difficult>0</difficult>
		<bndbox>
			<xmin>252</xmin>
			<ymin>844</ymin>
			<xmax>397</xmax>
			<ymax>1022</ymax>
		</bndbox>
	</object>
	<object>
		<name>Perching</name>
		<pose>Unspecified</pose>
		<truncated>0</truncated>
		<difficult>0</difficult>
		<bndbox>
			<xmin>765</xmin>
			<ymin>0</ymin>
			<xmax>960</xmax>
			<ymax>300</ymax>
		</bndbox>
	</object>
	<object>
		<name>Perching</name>
		<pose>Unspecified</pose>
		<truncated>0</truncated>
		<difficult>0</difficult>
		<bndbox>
			<xmin>1041</xmin>
			<ymin>50</ymin>
			<xmax>1154</xmax>
			<ymax>254</ymax>
		</bndbox>
	</object>
	<object>
		<name>Perching</name>
		<pose>Unspecified</pose>
		<truncated>0</truncated>
		<difficult>0</difficult>
		<bndbox>
			<xmin>1136</xmin>
			<ymin>95</ymin>
			<xmax>1250</xmax>
			<ymax>261</ymax>
		</bndbox>
	</object>
	<object>
		<name>Perching</name>
		<pose>Unspecified</pose>
		<truncated>0</truncated>
		<difficult>0</difficult>
		<bndbox>
			<xmin>1444</xmin>
			<ymin>60</ymin>
			<xmax>1556</xmax>
			<ymax>298</ymax>
		</bndbox>
	</object>
	<object>
		<name>Perching</name>
		<pose>Unspecified</pose>
		<truncated>0</truncated>
		<difficult>0</difficult>
		<bndbox>
			<xmin>687</xmin>
			<ymin>627</ymin>
			<xmax>852</xmax>
			<ymax>873</ymax>
		</bndbox>
	</object>
	<object>
		<name>Perching</name>
		<pose>Unspecified</pose>
		<truncated>0</truncated>
		<difficult>0</difficult>
		<bndbox>
			<xmin>960</xmin>
			<ymin>598</ymin>
			<xmax>1099</xmax>
			<ymax>871</ymax>
		</bndbox>
	</object>
	<object>
		<name>Perching</name>
		<pose>Unspecified</pose>
		<truncated>0</truncated>
		<difficult>0</difficult>
		<bndbox>
			<xmin>894</xmin>
			<ymin>749</ymin>
			<xmax>1072</xmax>
			<ymax>997</ymax>
		</bndbox>
	</object>
	<object>
		<name>Perching</name>
		<pose>Unspecified</pose>
		<truncated>0</truncated>
		<difficult>0</difficult>
		<bndbox>
			<xmin>1159</xmin>
			<ymin>706</ymin>
			<xmax>1328</xmax>
			<ymax>987</ymax>
		</bndbox>
	</object>
	<object>
		<name>Perching</name>
		<pose>Unspecified</pose>
		<truncated>0</truncated>
		<difficult>0</difficult>
		<bndbox>
			<xmin>1308</xmin>
			<ymin>724</ymin>
			<xmax>1407</xmax>
			<ymax>933</ymax>
		</bndbox>
	</object>
	<object>
		<name>Perching</name>
		<pose>Unspecified</pose>
		<truncated>0</truncated>
		<difficult>0</difficult>
		<bndbox>
			<xmin>1394</xmin>
			<ymin>768</ymin>
			<xmax>1552</xmax>
			<ymax>991</ymax>
		</bndbox>
	</object>
	<object>
		<name>Perching</name>
		<pose>Unspecified</pose>
		<truncated>0</truncated>
		<difficult>0</difficult>
		<bndbox>
			<xmin>1519</xmin>
			<ymin>685</ymin>
			<xmax>1668</xmax>
			<ymax>989</ymax>
		</bndbox>
	</object>
	<object>
		<name>Perching</name>
		<pose>Unspecified</pose>
		<truncated>0</truncated>
		<difficult>0</difficult>
		<bndbox>
			<xmin>1637</xmin>
			<ymin>718</ymin>
			<xmax>1719</xmax>
			<ymax>917</ymax>
		</bndbox>
	</object>
</annotation>